<?xml version="1.0" encoding="utf-8" ?>
<hibernate-mapping xmlns="urn:nhibernate-mapping-2.2" assembly="YiQiWorkFlow.Domain" namespace="YiQiWorkFlow.Domain.Rt">
  <class name="RtPluPromotion" table="rt_plu_promotion" lazy="true" >
    <id name="Id" type="string" column="sp_number" >
	    <generator class="assigned" />
    </id>
	<property name="EnCode" column="en_code" type="string" />
	<property name="SpBeginDate" column="sp_begin_date" type="string" />
	<property name="SpEndDate" column="sp_end_date" type="string" />
	<property name="SpBeginTime" column="sp_begin_time" type="string" />
	<property name="SpEndTime" column="sp_end_time" type="string" />
	<property name="SpW1" column="sp_w1" type="string" />
	<property name="SpW2" column="sp_w2" type="string" />
	<property name="SpW3" column="sp_w3" type="string" />
	<property name="SpW4" column="sp_w4" type="string" />
	<property name="SpW5" column="sp_w5" type="string" />
	<property name="SpW6" column="sp_w6" type="string" />
	<property name="SpW7" column="sp_w7" type="string" />
	<property name="AdjustReason" column="adjust_reason" type="string" />
	<property name="CreateDate" column="create_date" type="System.DateTime" />
	<property name="Operator" column="operator" type="string" />
	<property name="Assessor" column="assessor" type="string" />
	<property name="IfExamine" column="if_examine" type="string" />
	<property name="ExamineDate" column="examine_date" type="System.DateTime" />
	<property name="OperatorDate" column="operator_date" type="System.DateTime" />
  </class>
</hibernate-mapping>

